{"v":"5.9.0","fr":30,"ip":0,"op":112,"w":1920,"h":1080,"nm":"render 2","ddd":0,"assets":[{"id":"comp_0","nm":"main","fr":30,"layers":[{"ddd":0,"ind":5,"ty":0,"nm":"icon 2","refId":"comp_1","sr":1,"ks":{"o":{"a":0,"k":100,"ix":11},"r":{"a":0,"k":0,"ix":10},"p":{"a":0,"k":[960,864,0],"ix":2,"l":2},"a":{"a":0,"k":[960,864,0],"ix":1,"l":2},"s":{"a":0,"k":[100,100,100],"ix":6,"l":2}},"ao":0,"w":1920,"h":1728,"ip":0,"op":327,"st":0,"bm":0}]},{"id":"comp_1","nm":"icon 2","fr":30,"layers":[{"ddd":0,"ind":1,"ty":0,"nm":"Layer 7","refId":"comp_2","sr":1,"ks":{"o":{"a":0,"k":100,"ix":11},"r":{"a":1,"k":[{"i":{"x":[0.296],"y":[1]},"o":{"x":[0.155],"y":[0]},"t":73,"s":[0]},{"t":96,"s":[65]}],"ix":10},"p":{"a":1,"k":[{"i":{"x":0.833,"y":1},"o":{"x":0.333,"y":0},"t":73,"s":[814.568,879.588,0],"to":[0,0,0],"ti":[0,0,0]},{"t":96,"s":[728.437,893.943,0]}],"ix":2,"l":2},"a":{"a":0,"k":[1033.485,555.588,0],"ix":1,"l":2},"s":{"a":1,"k":[{"i":{"x":[0.839,0.839,0.667],"y":[1,1,1]},"o":{"x":[0.333,0.333,0.333],"y":[0,0,0]},"t":73,"s":[100,100,100]},{"i":{"x":[0.44,0.44,0.667],"y":[1,1,1]},"o":{"x":[0.733,0.733,0.333],"y":[0,0,0]},"t":96,"s":[130,130,100]},{"i":{"x":[0.833,0.833,0.833],"y":[0.833,0.833,6]},"o":{"x":[0.167,0.167,0.167],"y":[0,0,0]},"t":104.728,"s":[170,170,100]},{"t":112,"s":[25,25,100]}],"ix":6,"l":2}},"ao":0,"w":1920,"h":1080,"ip":65,"op":330,"st":65,"bm":0},{"ddd":0,"ind":2,"ty":4,"nm":"Layer 6 Outlines","sr":1,"ks":{"o":{"a":0,"k":100,"ix":11},"r":{"a":0,"k":0,"ix":10},"p":{"a":0,"k":[753.396,864.389,0],"ix":2,"l":2},"a":{"a":0,"k":[56.62,48.159,0],"ix":1,"l":2},"s":{"a":0,"k":[100,100,100],"ix":6,"l":2}},"ao":0,"shapes":[{"ty":"gr","it":[{"ind":0,"ty":"sh","ix":1,"ks":{"a":1,"k":[{"i":{"x":0.093,"y":1},"o":{"x":0.333,"y":0},"t":57,"s":[{"i":[[-8.165,2.188],[-2.188,-8.165],[-2.922,-10.908],[0,0],[-2.766,-1.784],[-3.65,0.978],[0,0],[-10.757,3.575],[-0.298,0.079],[-2.187,-8.164],[8.165,-2.188],[10.056,-2.694],[0,0],[12.008,-1.663],[0.718,0],[0,8.453],[2.497,9.322],[0,0],[3.621,9.435],[0.141,0.528]],"o":[[8.165,-2.187],[2.922,10.908],[0,0],[0.852,3.178],[3.176,2.049],[0,0],[10.95,-2.934],[0.289,-0.096],[8.164,-2.188],[2.188,8.165],[-10.056,2.695],[0,0],[-11.711,3.138],[-0.692,0.095],[-8.453,0],[0,-9.649],[0,0],[-2.616,-9.763],[-0.191,-0.498],[-2.188,-8.165]],"v":[[-28.146,16.864],[-9.401,27.687],[-18.945,31.695],[-15.567,44.3],[-16.14,19.733],[-38.44,24.543],[-27.361,21.574],[-27.682,17.144],[-26.802,16.881],[-8.058,27.703],[-18.88,46.448],[-29.633,42.891],[-30.737,42.772],[-22.307,47.763],[-24.424,47.909],[-39.729,32.602],[-29.049,35.052],[-29.789,32.29],[-38.469,37.15],[-38.968,35.61]],"c":true}]},{"t":65,"s":[{"i":[[-8.165,2.188],[-2.188,-8.165],[-2.922,-10.908],[0,0],[-2.766,-1.784],[-3.65,0.978],[0,0],[-10.757,3.575],[-0.298,0.079],[-2.187,-8.164],[8.165,-2.188],[10.056,-2.694],[0,0],[12.008,-1.663],[0.718,0],[0,8.453],[2.497,9.322],[0,0],[3.621,9.435],[0.141,0.528]],"o":[[8.165,-2.187],[2.922,10.908],[0,0],[0.852,3.178],[3.176,2.049],[0,0],[10.95,-2.934],[0.289,-0.096],[8.164,-2.188],[2.188,8.165],[-10.056,2.695],[0,0],[-11.711,3.138],[-0.692,0.095],[-8.453,0],[0,-9.649],[0,0],[-2.616,-9.763],[-0.191,-0.498],[-2.188,-8.165]],"v":[[-43.36,-45.722],[-24.615,-34.899],[-25.86,-0.117],[-22.482,12.488],[-16.14,19.733],[-5.591,22.468],[5.489,19.499],[34.558,-0.145],[35.438,-0.408],[54.182,10.414],[43.36,29.159],[11.5,28.891],[10.156,29.252],[-22.307,47.763],[-24.424,47.909],[-39.729,32.602],[-35.964,3.24],[-36.705,0.478],[-53.684,-25.436],[-54.182,-26.976]],"c":true}]}],"ix":2},"nm":"Path 1","mn":"ADBE Vector Shape - Group","hd":false},{"ty":"fl","c":{"a":0,"k":[1,1,1,1],"ix":4},"o":{"a":0,"k":100,"ix":5},"r":1,"bm":0,"nm":"Fill 1","mn":"ADBE Vector Graphic - Fill","hd":false},{"ty":"tr","p":{"a":0,"k":[56.62,48.159],"ix":2},"a":{"a":0,"k":[0,0],"ix":1},"s":{"a":0,"k":[100,100],"ix":3},"r":{"a":0,"k":0,"ix":6},"o":{"a":0,"k":100,"ix":7},"sk":{"a":0,"k":0,"ix":4},"sa":{"a":0,"k":0,"ix":5},"nm":"Transform"}],"nm":"Group 1","np":2,"cix":2,"bm":0,"ix":1,"mn":"ADBE Vector Group","hd":false}],"ip":57,"op":66,"st":2,"bm":0},{"ddd":0,"ind":3,"ty":4,"nm":"Layer 3 Outlines 3","sr":1,"ks":{"o":{"a":0,"k":100,"ix":11},"r":{"a":0,"k":0,"ix":10},"p":{"a":1,"k":[{"i":{"x":0.211,"y":1},"o":{"x":0.277,"y":0},"t":28,"s":[729.526,896.238,0],"to":[0,0,0],"ti":[0,0,0]},{"i":{"x":0.852,"y":0},"o":{"x":0,"y":0},"t":38,"s":[823.45,869.023,0],"to":[0,0,0],"ti":[0,0,0]},{"i":{"x":0,"y":1},"o":{"x":0.444,"y":0.161},"t":43,"s":[825.528,867.716,0],"to":[0,0,0],"ti":[0,0,0]},{"i":{"x":0,"y":0},"o":{"x":0.76,"y":0.76},"t":54,"s":[729.526,896.238,0],"to":[0,0,0],"ti":[0,0,0]},{"i":{"x":0.667,"y":1},"o":{"x":0.76,"y":0},"t":57,"s":[729.526,896.238,0],"to":[0,0,0],"ti":[0,0,0]},{"t":65,"s":[714.866,831.726,0]}],"ix":2,"l":2},"a":{"a":0,"k":[34.516,34.517,0],"ix":1,"l":2},"s":{"a":0,"k":[47,47,100],"ix":6,"l":2}},"ao":0,"shapes":[{"ty":"gr","it":[{"ind":0,"ty":"sh","ix":1,"ks":{"a":0,"k":{"i":[[0,18.925],[-18.924,0],[0,-18.925],[18.925,0]],"o":[[0,-18.925],[18.925,0],[0,18.925],[-18.924,-0.002]],"v":[[-34.266,-0.002],[-0.001,-34.266],[34.266,-0.001],[-0.001,34.266]],"c":true},"ix":2},"nm":"Path 1","mn":"ADBE Vector Shape - Group","hd":false},{"ty":"fl","c":{"a":0,"k":[1,1,1,1],"ix":4},"o":{"a":0,"k":100,"ix":5},"r":1,"bm":0,"nm":"Fill 1","mn":"ADBE Vector Graphic - Fill","hd":false},{"ty":"tr","p":{"a":0,"k":[34.516,34.516],"ix":2},"a":{"a":0,"k":[0,0],"ix":1},"s":{"a":0,"k":[100,100],"ix":3},"r":{"a":0,"k":0,"ix":6},"o":{"a":0,"k":100,"ix":7},"sk":{"a":0,"k":0,"ix":4},"sa":{"a":0,"k":0,"ix":5},"nm":"Transform"}],"nm":"Group 1","np":2,"cix":2,"bm":0,"ix":1,"mn":"ADBE Vector Group","hd":false}],"ip":28,"op":58,"st":-2,"bm":0},{"ddd":0,"ind":4,"ty":4,"nm":"Layer 3 Outlines 2","sr":1,"ks":{"o":{"a":0,"k":100,"ix":11},"r":{"a":0,"k":0,"ix":10},"p":{"a":1,"k":[{"i":{"x":0.211,"y":1},"o":{"x":0.277,"y":0},"t":28,"s":[729.526,896.238,0],"to":[0,0,0],"ti":[0,0,0]},{"i":{"x":0.211,"y":0.211},"o":{"x":0,"y":0},"t":38,"s":[711.534,825.782,0],"to":[0,0,0],"ti":[0,0,0]},{"i":{"x":0,"y":1},"o":{"x":0,"y":0},"t":43,"s":[711.534,825.782,0],"to":[0,0,0],"ti":[0,0,0]},{"i":{"x":0,"y":0},"o":{"x":0.76,"y":0.76},"t":54,"s":[729.526,896.238,0],"to":[0,0,0],"ti":[0,0,0]},{"i":{"x":0.667,"y":1},"o":{"x":0.76,"y":0},"t":57,"s":[729.526,896.238,0],"to":[0,0,0],"ti":[0,0,0]},{"t":65,"s":[794.196,877.491,0]}],"ix":2,"l":2},"a":{"a":0,"k":[34.516,34.517,0],"ix":1,"l":2},"s":{"a":0,"k":[47,47,100],"ix":6,"l":2}},"ao":0,"shapes":[{"ty":"gr","it":[{"ind":0,"ty":"sh","ix":1,"ks":{"a":0,"k":{"i":[[0,18.925],[-18.924,0],[0,-18.925],[18.925,0]],"o":[[0,-18.925],[18.925,0],[0,18.925],[-18.924,-0.002]],"v":[[-34.266,-0.002],[-0.001,-34.266],[34.266,-0.001],[-0.001,34.266]],"c":true},"ix":2},"nm":"Path 1","mn":"ADBE Vector Shape - Group","hd":false},{"ty":"fl","c":{"a":0,"k":[1,1,1,1],"ix":4},"o":{"a":0,"k":100,"ix":5},"r":1,"bm":0,"nm":"Fill 1","mn":"ADBE Vector Graphic - Fill","hd":false},{"ty":"tr","p":{"a":0,"k":[34.516,34.516],"ix":2},"a":{"a":0,"k":[0,0],"ix":1},"s":{"a":0,"k":[100,100],"ix":3},"r":{"a":0,"k":0,"ix":6},"o":{"a":0,"k":100,"ix":7},"sk":{"a":0,"k":0,"ix":4},"sa":{"a":0,"k":0,"ix":5},"nm":"Transform"}],"nm":"Group 1","np":2,"cix":2,"bm":0,"ix":1,"mn":"ADBE Vector Group","hd":false}],"ip":28,"op":58,"st":-2,"bm":0},{"ddd":0,"ind":5,"ty":4,"nm":"Layer 3 Outlines","sr":1,"ks":{"o":{"a":1,"k":[{"i":{"x":[0.833],"y":[0.833]},"o":{"x":[0.167],"y":[0.167]},"t":63,"s":[100]},{"t":65,"s":[0]}],"ix":11},"r":{"a":0,"k":0,"ix":10},"p":{"a":0,"k":[729.526,896.238,0],"ix":2,"l":2},"a":{"a":0,"k":[34.516,34.517,0],"ix":1,"l":2},"s":{"a":0,"k":[47,47,100],"ix":6,"l":2}},"ao":0,"shapes":[{"ty":"gr","it":[{"ind":0,"ty":"sh","ix":1,"ks":{"a":0,"k":{"i":[[0,18.925],[-18.924,0],[0,-18.925],[18.925,0]],"o":[[0,-18.925],[18.925,0],[0,18.925],[-18.924,-0.002]],"v":[[-34.266,-0.002],[-0.001,-34.266],[34.266,-0.001],[-0.001,34.266]],"c":true},"ix":2},"nm":"Path 1","mn":"ADBE Vector Shape - Group","hd":false},{"ty":"fl","c":{"a":0,"k":[1,1,1,1],"ix":4},"o":{"a":0,"k":100,"ix":5},"r":1,"bm":0,"nm":"Fill 1","mn":"ADBE Vector Graphic - Fill","hd":false},{"ty":"tr","p":{"a":0,"k":[34.516,34.516],"ix":2},"a":{"a":0,"k":[0,0],"ix":1},"s":{"a":0,"k":[100,100],"ix":3},"r":{"a":0,"k":0,"ix":6},"o":{"a":0,"k":100,"ix":7},"sk":{"a":0,"k":0,"ix":4},"sa":{"a":0,"k":0,"ix":5},"nm":"Transform"}],"nm":"Group 1","np":2,"cix":2,"bm":0,"ix":1,"mn":"ADBE Vector Group","hd":false}],"ip":28,"op":65,"st":-2,"bm":0},{"ddd":0,"ind":6,"ty":4,"nm":"Layer 2 Outlines 2","sr":1,"ks":{"o":{"a":0,"k":100,"ix":11},"r":{"a":0,"k":0,"ix":10},"p":{"a":1,"k":[{"i":{"x":0.828,"y":1},"o":{"x":0.28,"y":0},"t":0,"s":[729.182,895.216,0],"to":[0,0,0],"ti":[0,0,0]},{"i":{"x":0,"y":1},"o":{"x":0.084,"y":0},"t":5,"s":[729.182,1003.947,0],"to":[0,0,0],"ti":[0,0,0]},{"i":{"x":0.937,"y":1},"o":{"x":1,"y":0},"t":15,"s":[729.182,683.216,0],"to":[0,0,0],"ti":[0,0,0]},{"i":{"x":0,"y":0},"o":{"x":0.995,"y":0.995},"t":22,"s":[729.526,992.238,0],"to":[0,0,0],"ti":[0,0,0]},{"i":{"x":0.708,"y":1},"o":{"x":0.995,"y":0},"t":24,"s":[729.526,992.238,0],"to":[0,0,0],"ti":[0,0,0]},{"i":{"x":0.667,"y":1},"o":{"x":0.76,"y":0},"t":28,"s":[729.526,896.238,0],"to":[0,0,0],"ti":[0,0,0]},{"t":32,"s":[729.182,895.216,0]}],"ix":2,"l":2},"a":{"a":0,"k":[34.516,34.517,0],"ix":1,"l":2},"s":{"a":1,"k":[{"i":{"x":[0.833,0.833,0.833],"y":[1,1,1]},"o":{"x":[1,1,0.333],"y":[2.62,2.62,0]},"t":15,"s":[100,100,100]},{"i":{"x":[0.833,0.833,0.833],"y":[1,1,1]},"o":{"x":[1,1,0.333],"y":[0,0,0]},"t":22,"s":[100,100,100]},{"i":{"x":[0.667,0.667,0.667],"y":[1,1,1]},"o":{"x":[1,1,0.333],"y":[0,0,0]},"t":24,"s":[100,100,100]},{"t":28,"s":[47,47,100]}],"ix":6,"l":2}},"ao":0,"shapes":[{"ty":"gr","it":[{"ind":0,"ty":"sh","ix":1,"ks":{"a":0,"k":{"i":[[0,18.925],[-18.924,0],[0,-18.925],[18.925,0]],"o":[[0,-18.925],[18.925,0],[0,18.925],[-18.924,-0.002]],"v":[[-34.266,-0.002],[-0.001,-34.266],[34.266,-0.001],[-0.001,34.266]],"c":true},"ix":2},"nm":"Path 1","mn":"ADBE Vector Shape - Group","hd":false},{"ty":"fl","c":{"a":0,"k":[1,1,1,1],"ix":4},"o":{"a":0,"k":100,"ix":5},"r":1,"bm":0,"nm":"Fill 1","mn":"ADBE Vector Graphic - Fill","hd":false},{"ty":"tr","p":{"a":0,"k":[34.516,34.516],"ix":2},"a":{"a":0,"k":[0,0],"ix":1},"s":{"a":0,"k":[100,100],"ix":3},"r":{"a":0,"k":0,"ix":6},"o":{"a":0,"k":100,"ix":7},"sk":{"a":0,"k":0,"ix":4},"sa":{"a":0,"k":0,"ix":5},"nm":"Transform"}],"nm":"Group 1","np":2,"cix":2,"bm":0,"ix":1,"mn":"ADBE Vector Group","hd":false}],"ip":0,"op":38,"st":0,"bm":0},{"ddd":0,"ind":7,"ty":4,"nm":"Layer 2 Outlines","sr":1,"ks":{"o":{"a":0,"k":100,"ix":11},"r":{"a":0,"k":0,"ix":10},"p":{"a":1,"k":[{"i":{"x":0.828,"y":1},"o":{"x":0.28,"y":0},"t":112,"s":[729.182,895.216,0],"to":[0,0,0],"ti":[0,0,0]},{"i":{"x":0,"y":1},"o":{"x":0.084,"y":0},"t":117,"s":[729.182,1003.947,0],"to":[0,0,0],"ti":[0,0,0]},{"i":{"x":0.937,"y":1},"o":{"x":1,"y":0},"t":127,"s":[729.182,683.216,0],"to":[0,0,0],"ti":[0,0,0]},{"i":{"x":0,"y":0},"o":{"x":0.995,"y":0.995},"t":134,"s":[729.526,992.238,0],"to":[0,0,0],"ti":[0,0,0]},{"i":{"x":0.708,"y":1},"o":{"x":0.995,"y":0},"t":136,"s":[729.526,992.238,0],"to":[0,0,0],"ti":[0,0,0]},{"i":{"x":0.667,"y":1},"o":{"x":0.76,"y":0},"t":140,"s":[729.526,896.238,0],"to":[0,0,0],"ti":[0,0,0]},{"t":144,"s":[729.182,895.216,0]}],"ix":2,"l":2},"a":{"a":0,"k":[34.516,34.517,0],"ix":1,"l":2},"s":{"a":1,"k":[{"i":{"x":[0.833,0.833,0.833],"y":[1,1,1]},"o":{"x":[1,1,0.333],"y":[2.62,2.62,0]},"t":127,"s":[100,100,100]},{"i":{"x":[0.833,0.833,0.833],"y":[1,1,1]},"o":{"x":[1,1,0.333],"y":[0,0,0]},"t":134,"s":[100,100,100]},{"i":{"x":[0.667,0.667,0.667],"y":[1,1,1]},"o":{"x":[1,1,0.333],"y":[0,0,0]},"t":136,"s":[100,100,100]},{"t":140,"s":[47,47,100]}],"ix":6,"l":2}},"ao":0,"shapes":[{"ty":"gr","it":[{"ind":0,"ty":"sh","ix":1,"ks":{"a":0,"k":{"i":[[0,18.925],[-18.924,0],[0,-18.925],[18.925,0]],"o":[[0,-18.925],[18.925,0],[0,18.925],[-18.924,-0.002]],"v":[[-34.266,-0.002],[-0.001,-34.266],[34.266,-0.001],[-0.001,34.266]],"c":true},"ix":2},"nm":"Path 1","mn":"ADBE Vector Shape - Group","hd":false},{"ty":"fl","c":{"a":0,"k":[1,1,1,1],"ix":4},"o":{"a":0,"k":100,"ix":5},"r":1,"bm":0,"nm":"Fill 1","mn":"ADBE Vector Graphic - Fill","hd":false},{"ty":"tr","p":{"a":0,"k":[34.516,34.516],"ix":2},"a":{"a":0,"k":[0,0],"ix":1},"s":{"a":0,"k":[100,100],"ix":3},"r":{"a":0,"k":0,"ix":6},"o":{"a":0,"k":100,"ix":7},"sk":{"a":0,"k":0,"ix":4},"sa":{"a":0,"k":0,"ix":5},"nm":"Transform"}],"nm":"Group 1","np":2,"cix":2,"bm":0,"ix":1,"mn":"ADBE Vector Group","hd":false}],"ip":112,"op":150,"st":112,"bm":0}]},{"id":"comp_2","nm":"Layer 7","fr":30,"layers":[{"ddd":0,"ind":1,"ty":4,"nm":"Layer 6 Outlines 7","sr":1,"ks":{"o":{"a":1,"k":[{"i":{"x":[0.833],"y":[0.833]},"o":{"x":[0.167],"y":[0.167]},"t":25,"s":[0]},{"t":28,"s":[100]}],"ix":11},"r":{"a":1,"k":[{"i":{"x":[0.667],"y":[1]},"o":{"x":[0.822],"y":[0]},"t":25,"s":[465]},{"t":28,"s":[524]}],"ix":10},"p":{"a":1,"k":[{"i":{"x":0.667,"y":1},"o":{"x":0.811,"y":0},"t":25,"s":[1000.491,503.33,0],"to":[0,0,0],"ti":[0,0,0]},{"t":28,"s":[1060.724,498.148,0]}],"ix":2,"l":2},"a":{"a":0,"k":[16.461,16.328,0],"ix":1,"l":2},"s":{"a":0,"k":[100,100,100],"ix":6,"l":2}},"ao":0,"shapes":[{"ty":"gr","it":[{"ind":0,"ty":"sh","ix":1,"ks":{"a":0,"k":{"i":[[-8.165,2.188],[-2.188,-8.165],[-2.922,-10.908],[0,0],[-2.766,-1.784],[-3.65,0.978],[0,0],[-10.757,3.575],[-0.298,0.079],[-2.187,-8.164],[8.165,-2.188],[10.056,-2.694],[0,0],[12.008,-1.663],[0.718,0],[0,8.453],[2.497,9.322],[0,0],[3.621,9.435],[0.141,0.528]],"o":[[8.165,-2.187],[2.922,10.908],[0,0],[0.852,3.178],[3.176,2.049],[0,0],[10.95,-2.934],[0.289,-0.096],[8.164,-2.188],[2.188,8.165],[-10.056,2.695],[0,0],[-11.711,3.138],[-0.692,0.095],[-8.453,0],[0,-9.649],[0,0],[-2.616,-9.763],[-0.191,-0.498],[-2.188,-8.165]],"v":[[-43.36,-45.722],[-24.615,-34.899],[-25.86,-0.117],[-22.482,12.488],[-16.14,19.733],[-5.591,22.468],[5.489,19.499],[34.558,-0.145],[35.438,-0.408],[54.182,10.414],[43.36,29.159],[11.5,28.891],[10.156,29.252],[-22.307,47.763],[-24.424,47.909],[-39.729,32.602],[-35.964,3.24],[-36.705,0.478],[-53.684,-25.436],[-54.182,-26.976]],"c":true},"ix":2},"nm":"Path 1","mn":"ADBE Vector Shape - Group","hd":false},{"ty":"fl","c":{"a":0,"k":[1,1,1,1],"ix":4},"o":{"a":0,"k":100,"ix":5},"r":1,"bm":0,"nm":"Fill 1","mn":"ADBE Vector Graphic - Fill","hd":false},{"ty":"tr","p":{"a":0,"k":[56.62,48.159],"ix":2},"a":{"a":0,"k":[0,0],"ix":1},"s":{"a":0,"k":[100,100],"ix":3},"r":{"a":0,"k":0,"ix":6},"o":{"a":0,"k":100,"ix":7},"sk":{"a":0,"k":0,"ix":4},"sa":{"a":0,"k":0,"ix":5},"nm":"Transform"}],"nm":"Group 1","np":2,"cix":2,"bm":0,"ix":1,"mn":"ADBE Vector Group","hd":false}],"ip":25,"op":264,"st":-80,"bm":0},{"ddd":0,"ind":2,"ty":4,"nm":"Layer 6 Outlines 6","sr":1,"ks":{"o":{"a":1,"k":[{"i":{"x":[0.833],"y":[0.833]},"o":{"x":[0.167],"y":[0.167]},"t":21,"s":[0]},{"t":25,"s":[100]}],"ix":11},"r":{"a":1,"k":[{"i":{"x":[0.667],"y":[1]},"o":{"x":[0.822],"y":[0]},"t":21,"s":[405]},{"t":25,"s":[465]}],"ix":10},"p":{"a":1,"k":[{"i":{"x":0.667,"y":1},"o":{"x":0.822,"y":0},"t":21,"s":[974.491,555.33,0],"to":[0,0,0],"ti":[0,0,0]},{"t":25,"s":[1000.491,503.33,0]}],"ix":2,"l":2},"a":{"a":0,"k":[16.461,16.328,0],"ix":1,"l":2},"s":{"a":0,"k":[100,100,100],"ix":6,"l":2}},"ao":0,"shapes":[{"ty":"gr","it":[{"ind":0,"ty":"sh","ix":1,"ks":{"a":0,"k":{"i":[[-8.165,2.188],[-2.188,-8.165],[-2.922,-10.908],[0,0],[-2.766,-1.784],[-3.65,0.978],[0,0],[-10.757,3.575],[-0.298,0.079],[-2.187,-8.164],[8.165,-2.188],[10.056,-2.694],[0,0],[12.008,-1.663],[0.718,0],[0,8.453],[2.497,9.322],[0,0],[3.621,9.435],[0.141,0.528]],"o":[[8.165,-2.187],[2.922,10.908],[0,0],[0.852,3.178],[3.176,2.049],[0,0],[10.95,-2.934],[0.289,-0.096],[8.164,-2.188],[2.188,8.165],[-10.056,2.695],[0,0],[-11.711,3.138],[-0.692,0.095],[-8.453,0],[0,-9.649],[0,0],[-2.616,-9.763],[-0.191,-0.498],[-2.188,-8.165]],"v":[[-43.36,-45.722],[-24.615,-34.899],[-25.86,-0.117],[-22.482,12.488],[-16.14,19.733],[-5.591,22.468],[5.489,19.499],[34.558,-0.145],[35.438,-0.408],[54.182,10.414],[43.36,29.159],[11.5,28.891],[10.156,29.252],[-22.307,47.763],[-24.424,47.909],[-39.729,32.602],[-35.964,3.24],[-36.705,0.478],[-53.684,-25.436],[-54.182,-26.976]],"c":true},"ix":2},"nm":"Path 1","mn":"ADBE Vector Shape - Group","hd":false},{"ty":"fl","c":{"a":0,"k":[1,1,1,1],"ix":4},"o":{"a":0,"k":100,"ix":5},"r":1,"bm":0,"nm":"Fill 1","mn":"ADBE Vector Graphic - Fill","hd":false},{"ty":"tr","p":{"a":0,"k":[56.62,48.159],"ix":2},"a":{"a":0,"k":[0,0],"ix":1},"s":{"a":0,"k":[100,100],"ix":3},"r":{"a":0,"k":0,"ix":6},"o":{"a":0,"k":100,"ix":7},"sk":{"a":0,"k":0,"ix":4},"sa":{"a":0,"k":0,"ix":5},"nm":"Transform"}],"nm":"Group 1","np":2,"cix":2,"bm":0,"ix":1,"mn":"ADBE Vector Group","hd":false}],"ip":21,"op":263,"st":-76,"bm":0},{"ddd":0,"ind":3,"ty":4,"nm":"Layer 6 Outlines 5","sr":1,"ks":{"o":{"a":1,"k":[{"i":{"x":[0.833],"y":[0.833]},"o":{"x":[0.167],"y":[0.167]},"t":18,"s":[0]},{"t":23,"s":[100]}],"ix":11},"r":{"a":1,"k":[{"i":{"x":[0.667],"y":[1]},"o":{"x":[0.916],"y":[0]},"t":18,"s":[345]},{"t":23,"s":[405]}],"ix":10},"p":{"a":1,"k":[{"i":{"x":0.667,"y":1},"o":{"x":0.892,"y":0},"t":18,"s":[1013.241,607.83,0],"to":[0,0,0],"ti":[0,0,0]},{"t":23,"s":[974.491,555.33,0]}],"ix":2,"l":2},"a":{"a":0,"k":[16.461,16.328,0],"ix":1,"l":2},"s":{"a":0,"k":[100,100,100],"ix":6,"l":2}},"ao":0,"shapes":[{"ty":"gr","it":[{"ind":0,"ty":"sh","ix":1,"ks":{"a":0,"k":{"i":[[-8.165,2.188],[-2.188,-8.165],[-2.922,-10.908],[0,0],[-2.766,-1.784],[-3.65,0.978],[0,0],[-10.757,3.575],[-0.298,0.079],[-2.187,-8.164],[8.165,-2.188],[10.056,-2.694],[0,0],[12.008,-1.663],[0.718,0],[0,8.453],[2.497,9.322],[0,0],[3.621,9.435],[0.141,0.528]],"o":[[8.165,-2.187],[2.922,10.908],[0,0],[0.852,3.178],[3.176,2.049],[0,0],[10.95,-2.934],[0.289,-0.096],[8.164,-2.188],[2.188,8.165],[-10.056,2.695],[0,0],[-11.711,3.138],[-0.692,0.095],[-8.453,0],[0,-9.649],[0,0],[-2.616,-9.763],[-0.191,-0.498],[-2.188,-8.165]],"v":[[-43.36,-45.722],[-24.615,-34.899],[-25.86,-0.117],[-22.482,12.488],[-16.14,19.733],[-5.591,22.468],[5.489,19.499],[34.558,-0.145],[35.438,-0.408],[54.182,10.414],[43.36,29.159],[11.5,28.891],[10.156,29.252],[-22.307,47.763],[-24.424,47.909],[-39.729,32.602],[-35.964,3.24],[-36.705,0.478],[-53.684,-25.436],[-54.182,-26.976]],"c":true},"ix":2},"nm":"Path 1","mn":"ADBE Vector Shape - Group","hd":false},{"ty":"fl","c":{"a":0,"k":[1,1,1,1],"ix":4},"o":{"a":0,"k":100,"ix":5},"r":1,"bm":0,"nm":"Fill 1","mn":"ADBE Vector Graphic - Fill","hd":false},{"ty":"tr","p":{"a":0,"k":[56.62,48.159],"ix":2},"a":{"a":0,"k":[0,0],"ix":1},"s":{"a":0,"k":[100,100],"ix":3},"r":{"a":0,"k":0,"ix":6},"o":{"a":0,"k":100,"ix":7},"sk":{"a":0,"k":0,"ix":4},"sa":{"a":0,"k":0,"ix":5},"nm":"Transform"}],"nm":"Group 1","np":2,"cix":2,"bm":0,"ix":1,"mn":"ADBE Vector Group","hd":false}],"ip":18,"op":263,"st":-72,"bm":0},{"ddd":0,"ind":4,"ty":4,"nm":"Layer 6 Outlines 4","sr":1,"ks":{"o":{"a":1,"k":[{"i":{"x":[0.833],"y":[0.833]},"o":{"x":[0.167],"y":[0.167]},"t":13,"s":[0]},{"t":20,"s":[100]}],"ix":11},"r":{"a":1,"k":[{"i":{"x":[0.667],"y":[1]},"o":{"x":[0.892],"y":[0]},"t":13,"s":[285]},{"t":20,"s":[345]}],"ix":10},"p":{"a":1,"k":[{"i":{"x":0.667,"y":1},"o":{"x":0.892,"y":0},"t":13,"s":[1070.241,605.83,0],"to":[0,0,0],"ti":[0,0,0]},{"t":20,"s":[1012.472,606.804,0]}],"ix":2,"l":2},"a":{"a":0,"k":[16.461,16.328,0],"ix":1,"l":2},"s":{"a":0,"k":[100,100,100],"ix":6,"l":2}},"ao":0,"shapes":[{"ty":"gr","it":[{"ind":0,"ty":"sh","ix":1,"ks":{"a":0,"k":{"i":[[-8.165,2.188],[-2.188,-8.165],[-2.922,-10.908],[0,0],[-2.766,-1.784],[-3.65,0.978],[0,0],[-10.757,3.575],[-0.298,0.079],[-2.187,-8.164],[8.165,-2.188],[10.056,-2.694],[0,0],[12.008,-1.663],[0.718,0],[0,8.453],[2.497,9.322],[0,0],[3.621,9.435],[0.141,0.528]],"o":[[8.165,-2.187],[2.922,10.908],[0,0],[0.852,3.178],[3.176,2.049],[0,0],[10.95,-2.934],[0.289,-0.096],[8.164,-2.188],[2.188,8.165],[-10.056,2.695],[0,0],[-11.711,3.138],[-0.692,0.095],[-8.453,0],[0,-9.649],[0,0],[-2.616,-9.763],[-0.191,-0.498],[-2.188,-8.165]],"v":[[-43.36,-45.722],[-24.615,-34.899],[-25.86,-0.117],[-22.482,12.488],[-16.14,19.733],[-5.591,22.468],[5.489,19.499],[34.558,-0.145],[35.438,-0.408],[54.182,10.414],[43.36,29.159],[11.5,28.891],[10.156,29.252],[-22.307,47.763],[-24.424,47.909],[-39.729,32.602],[-35.964,3.24],[-36.705,0.478],[-53.684,-25.436],[-54.182,-26.976]],"c":true},"ix":2},"nm":"Path 1","mn":"ADBE Vector Shape - Group","hd":false},{"ty":"fl","c":{"a":0,"k":[1,1,1,1],"ix":4},"o":{"a":0,"k":100,"ix":5},"r":1,"bm":0,"nm":"Fill 1","mn":"ADBE Vector Graphic - Fill","hd":false},{"ty":"tr","p":{"a":0,"k":[56.62,48.159],"ix":2},"a":{"a":0,"k":[0,0],"ix":1},"s":{"a":0,"k":[100,100],"ix":3},"r":{"a":0,"k":0,"ix":6},"o":{"a":0,"k":100,"ix":7},"sk":{"a":0,"k":0,"ix":4},"sa":{"a":0,"k":0,"ix":5},"nm":"Transform"}],"nm":"Group 1","np":2,"cix":2,"bm":0,"ix":1,"mn":"ADBE Vector Group","hd":false}],"ip":13,"op":265,"st":-70,"bm":0},{"ddd":0,"ind":5,"ty":4,"nm":"Layer 6 Outlines 3","sr":1,"ks":{"o":{"a":1,"k":[{"i":{"x":[0.667],"y":[1]},"o":{"x":[0.333],"y":[0]},"t":8,"s":[0]},{"t":16,"s":[100]}],"ix":11},"r":{"a":1,"k":[{"i":{"x":[0.667],"y":[1]},"o":{"x":[0.937],"y":[0]},"t":8,"s":[226]},{"t":16,"s":[285]}],"ix":10},"p":{"a":1,"k":[{"i":{"x":0.667,"y":1},"o":{"x":0.937,"y":0},"t":8,"s":[1095.147,549.994,0],"to":[0,0,0],"ti":[0,0,0]},{"t":16,"s":[1067.853,605.488,0]}],"ix":2,"l":2},"a":{"a":0,"k":[16.461,16.328,0],"ix":1,"l":2},"s":{"a":0,"k":[100,100,100],"ix":6,"l":2}},"ao":0,"shapes":[{"ty":"gr","it":[{"ind":0,"ty":"sh","ix":1,"ks":{"a":0,"k":{"i":[[-8.165,2.188],[-2.188,-8.165],[-2.922,-10.908],[0,0],[-2.766,-1.784],[-3.65,0.978],[0,0],[-10.757,3.575],[-0.298,0.079],[-2.187,-8.164],[8.165,-2.188],[10.056,-2.694],[0,0],[12.008,-1.663],[0.718,0],[0,8.453],[2.497,9.322],[0,0],[3.621,9.435],[0.141,0.528]],"o":[[8.165,-2.187],[2.922,10.908],[0,0],[0.852,3.178],[3.176,2.049],[0,0],[10.95,-2.934],[0.289,-0.096],[8.164,-2.188],[2.188,8.165],[-10.056,2.695],[0,0],[-11.711,3.138],[-0.692,0.095],[-8.453,0],[0,-9.649],[0,0],[-2.616,-9.763],[-0.191,-0.498],[-2.188,-8.165]],"v":[[-43.36,-45.722],[-24.615,-34.899],[-25.86,-0.117],[-22.482,12.488],[-16.14,19.733],[-5.591,22.468],[5.489,19.499],[34.558,-0.145],[35.438,-0.408],[54.182,10.414],[43.36,29.159],[11.5,28.891],[10.156,29.252],[-22.307,47.763],[-24.424,47.909],[-39.729,32.602],[-35.964,3.24],[-36.705,0.478],[-53.684,-25.436],[-54.182,-26.976]],"c":true},"ix":2},"nm":"Path 1","mn":"ADBE Vector Shape - Group","hd":false},{"ty":"fl","c":{"a":0,"k":[1,1,1,1],"ix":4},"o":{"a":0,"k":100,"ix":5},"r":1,"bm":0,"nm":"Fill 1","mn":"ADBE Vector Graphic - Fill","hd":false},{"ty":"tr","p":{"a":0,"k":[56.62,48.159],"ix":2},"a":{"a":0,"k":[0,0],"ix":1},"s":{"a":0,"k":[100,100],"ix":3},"r":{"a":0,"k":0,"ix":6},"o":{"a":0,"k":100,"ix":7},"sk":{"a":0,"k":0,"ix":4},"sa":{"a":0,"k":0,"ix":5},"nm":"Transform"}],"nm":"Group 1","np":2,"cix":2,"bm":0,"ix":1,"mn":"ADBE Vector Group","hd":false}],"ip":8,"op":266,"st":-67,"bm":0},{"ddd":0,"ind":6,"ty":4,"nm":"Layer 6 Outlines 2","sr":1,"ks":{"o":{"a":0,"k":100,"ix":11},"r":{"a":1,"k":[{"i":{"x":[0.667],"y":[1]},"o":{"x":[0.333],"y":[0]},"t":0,"s":[0]},{"t":12,"s":[226]}],"ix":10},"p":{"a":1,"k":[{"i":{"x":0.667,"y":1},"o":{"x":0.333,"y":0},"t":0,"s":[972.312,540.389,0],"to":[0,0,0],"ti":[0,0,0]},{"t":12,"s":[1090.241,498.83,0]}],"ix":2,"l":2},"a":{"a":0,"k":[56.62,48.159,0],"ix":1,"l":2},"s":{"a":0,"k":[100,100,100],"ix":6,"l":2}},"ao":0,"shapes":[{"ty":"gr","it":[{"ind":0,"ty":"sh","ix":1,"ks":{"a":0,"k":{"i":[[-8.165,2.188],[-2.188,-8.165],[-2.922,-10.908],[0,0],[-2.766,-1.784],[-3.65,0.978],[0,0],[-10.757,3.575],[-0.298,0.079],[-2.187,-8.164],[8.165,-2.188],[10.056,-2.694],[0,0],[12.008,-1.663],[0.718,0],[0,8.453],[2.497,9.322],[0,0],[3.621,9.435],[0.141,0.528]],"o":[[8.165,-2.187],[2.922,10.908],[0,0],[0.852,3.178],[3.176,2.049],[0,0],[10.95,-2.934],[0.289,-0.096],[8.164,-2.188],[2.188,8.165],[-10.056,2.695],[0,0],[-11.711,3.138],[-0.692,0.095],[-8.453,0],[0,-9.649],[0,0],[-2.616,-9.763],[-0.191,-0.498],[-2.188,-8.165]],"v":[[-43.36,-45.722],[-24.615,-34.899],[-25.86,-0.117],[-22.482,12.488],[-16.14,19.733],[-5.591,22.468],[5.489,19.499],[34.558,-0.145],[35.438,-0.408],[54.182,10.414],[43.36,29.159],[11.5,28.891],[10.156,29.252],[-22.307,47.763],[-24.424,47.909],[-39.729,32.602],[-35.964,3.24],[-36.705,0.478],[-53.684,-25.436],[-54.182,-26.976]],"c":true},"ix":2},"nm":"Path 1","mn":"ADBE Vector Shape - Group","hd":false},{"ty":"fl","c":{"a":0,"k":[1,1,1,1],"ix":4},"o":{"a":0,"k":100,"ix":5},"r":1,"bm":0,"nm":"Fill 1","mn":"ADBE Vector Graphic - Fill","hd":false},{"ty":"tr","p":{"a":0,"k":[56.62,48.159],"ix":2},"a":{"a":0,"k":[0,0],"ix":1},"s":{"a":0,"k":[100,100],"ix":3},"r":{"a":0,"k":0,"ix":6},"o":{"a":0,"k":100,"ix":7},"sk":{"a":0,"k":0,"ix":4},"sa":{"a":0,"k":0,"ix":5},"nm":"Transform"}],"nm":"Group 1","np":2,"cix":2,"bm":0,"ix":1,"mn":"ADBE Vector Group","hd":false}],"ip":0,"op":266.473262032086,"st":-63,"bm":0}]}],"layers":[{"ddd":0,"ind":1,"ty":0,"nm":"main","refId":"comp_0","sr":1,"ks":{"o":{"a":0,"k":100,"ix":11},"r":{"a":0,"k":0,"ix":10},"p":{"a":0,"k":[1169.259,540,0],"ix":2,"l":2},"a":{"a":0,"k":[960,864,0],"ix":1,"l":2},"s":{"a":0,"k":[90,90,100],"ix":6,"l":2}},"ao":0,"w":1920,"h":1728,"ip":0,"op":327,"st":0,"bm":0}],"markers":[]}